{
    "jumbotron-heading" : "Automa&#231;&#227;o para Aplicativos"
  , "jumbotron-p-pt1" : "Appium &#233; um framework de automa&#231;&#227;o de teste de c&#243;digo aberto para uso com nativo e"
  , "jumbotron-p-pt2" : "hybrid"
  , "jumbotron-p-pt3" : " aplicativos m&#243;veis. "
  , "jumbotron-p-pt4" : "Dirige iOS e Android utilizando o WebDriver"
  , "jumbotron-p-pt5" : "JSON protocolo"
  , "jumbotron-p-pt6" : "."
  , "downloadLink" : "Baixe Appium"
  , "jumbotron-github" : "Ver em GitHub"
  , "jumbotron-downloads" : "Download Appium"
  , "jumbotron-examples" : "Exemplos"
  , "jumbotron-contributions" : "Contribui&#231;&#245;es"
  , "introducing-appium" : "Apresentando o Appium."
  , "intro-subheading" : "O aplicativo nativo automa&#231;&#227;o esta faltando em suas ferramentas? Problema resolvido."
  , "watch-videos" : "Assista os v&#237;deos"
  , "philosophy" : "Filosofia do Appium"
  , "philosophy-more" : "Appium &#233; baseado na id&#233;ia de testar aplicativos nativos, n&#227;o deve exigir um SDK ou recompilar seu aplicativos. E que voc&#234; deve ser capaz de usar suas pr&#225;ticas preferidas dos testes, frameworks e ferramentas. O Appium &#233; um projeto open source e tem feito decis&#245;es de desenho, ferramentas para incentivar a comunidade a contribuir vibrante."
  , "favorite-tools" : "Usar suas ferramentas favoritas"
  , "favorite-tools-more" : "Appium visa automatizar qualquer aplicativo m&#243;vel de qualquer idioma e em qualquer framework, com acesso total a back-end APIs e DBs de c&#243;digo. Escrever testes com suas ferramentas favoritas dev utilizando todas as linguagens de programa&#231;&#227;o, e tambem (com a Selenium WebDriver API e bibliotecas de cliente espec&#237;ficos do idioma)."
  , "requirements" : "Requisitos"
  , "easy-setup" : "O processo de configura&#231;&#227;o e muito f&#225;cil, voc&#234; pode executar um teste agora."
  , "easy-setup-p1" : "Instalar"
  , "easy-setup-p2" : "(includes npm, the node.js package manager)."
}
